adam_calculator_mcp/__init__.py
adam_calculator_mcp/__main__.py
adam_calculator_mcp-0.1.4.dist-info/METADATA
adam_calculator_mcp-0.1.4.dist-info/WHEEL
adam_calculator_mcp-0.1.4.dist-info/entry_points.txt
adam_calculator_mcp-0.1.4.dist-info/licenses/LICENSE
adam_calculator_mcp-0.1.4.dist-info/RECORD
