Metadata-Version: 2.4
Name: adam-calculator-mcp
Version: 0.1.4
Summary: adam 计算器 mcp 工具
Project-URL: Homepage, https://github.com/adam/adam-calculator-mcp
Project-URL: Repository, https://github.com/adam/adam-calculator-mcp
Project-URL: Issues, https://github.com/adam/adam-calculator-mcp/issues
Author-email: adam <adam@example.com>
License: MIT
License-File: LICENSE
Classifier: Development Status :: 3 - Alpha
Classifier: Intended Audience :: Developers
Classifier: License :: OSI Approved :: MIT License
Classifier: Programming Language :: Python :: 3
Classifier: Programming Language :: Python :: 3.10
Classifier: Programming Language :: Python :: 3.11
Classifier: Programming Language :: Python :: 3.12
Requires-Python: >=3.10
Requires-Dist: httpx>=0.28.1
Requires-Dist: mcp[cli]>=1.21.0
